[
    {
        "name": "Sayonara o Oshiete",
        "coverPath": "covers/76933.jpg",
        "exePath": "",
        "workingDir": "",
        "arguments": []
    },
    {
        "name": "Steins;Gate",
        "coverPath": "covers/77819.jpg",
        "exePath": "",
        "workingDir": "",
        "arguments": []
    },
    {
        "name": "Full Metal Daemon Muramasa",
        "coverPath": "covers/77925.jpg",
        "exePath": "F:/rar     gallllllllllll/恶鬼/【PC】装甲恶鬼村正.part1/装甲恶鬼村正/Muramasa_chs.exe",
        "workingDir": "",
        "arguments": []
    },
    {
        "name": "Nukitashi",
        "coverPath": "covers/78282.jpg",
        "exePath": "",
        "workingDir": "",
        "arguments": []
    },
    {
        "name": "Sabbat of the Witch",
        "coverPath": "covers/79952.jpg",
        "exePath": "",
        "workingDir": "",
        "arguments": []
    },
    {
        "name": "Subarashiki Hibi",
        "coverPath": "covers/90017.jpg",
        "exePath": "",
        "workingDir": "",
        "arguments": []
    },
    {
        "name": "Magical Girl Witch Trial",
        "coverPath": "covers/100334.jpg",
        "exePath": "",
        "workingDir": "",
        "arguments": []
    },
    {
        "name": "Saya no Uta",
        "coverPath": "covers/132772.jpg",
        "exePath": "",
        "workingDir": "",
        "arguments": []
    }
]
